{"type": "FeatureCollection", "features": [{"type": "Feature", "properties": {"id": "ea28057a-7fee-4924-908a-b3868a8fbd35", "name": "Johnny's South Bistro", "category": "bar", "tags": ["bar"], "sources": ["overture"], "address": "15028 116th Pl NE"}, "geometry": {"type": "Point", "coordinates": [-122.1852875, 47.7378006]}}, {"type": "Feature", "properties": {"id": 105539961, "name": "Bud Homan Park", "category": "park", "tags": ["park"], "sources": ["osm"], "address": "15305 119th Avenue Northeast"}, "geometry": {"type": "Point", "coordinates": [-122.1828499, 47.7393083]}}, {"type": "Feature", "properties": {"id": "a43df3c7-7922-4b0d-b28e-8f61192d01a0", "name": "High Woodlands Private Pool", "category": "swimming_pool", "tags": ["swimming-pool", "swimming", "pool"], "sources": ["overture"], "website": "http://www.highwoodlands.org/poolinfo.php", "phone": "+14258069119", "address": "11600 NE 148th Ct"}, "geometry": {"type": "Point", "coordinates": [-122.1858139, 47.7342377]}}]}