{"type": "FeatureCollection", "features": [{"type": "Feature", "properties": {"id": "190e8c38-b08b-48e1-be1d-4d5b5aadadfb", "name": "Starbucks", "category": "cafe", "tags": ["cafe", "coffee"], "sources": ["overture"], "website": "http://www.starbucks.com", "phone": "(425) 251-3393", "address": "7906 S 184th St"}, "geometry": {"type": "Point", "coordinates": [-122.2347412, 47.4378014]}}, {"type": "Feature", "properties": {"id": "34d58393-9ece-4d1a-8bbe-d4712a31bb2e", "name": "Starbucks", "category": "cafe", "tags": ["cafe", "coffee"], "sources": ["overture"], "website": "http://www.starbucks.com", "phone": "(425) 251-6961", "address": "7911 S 188th St"}, "geometry": {"type": "Point", "coordinates": [-122.2361374, 47.4328079]}}, {"type": "Feature", "properties": {"id": "7cdf65f1-3193-4cf4-8368-02eaa1186a51", "name": "Puratos Seattle", "category": "cafe", "tags": ["cafe", "coffee"], "sources": ["overture"], "website": "http://www.puratos.us/", "phone": "+12067625400", "address": "7915 S 184th St"}, "geometry": {"type": "Point", "coordinates": [-122.2343216, 47.4370346]}}, {"type": "Feature", "properties": {"id": "333d21dd-3e6c-4fb7-b1b9-0a46edd2a365", "name": "Convoy Supply Inc.", "category": "doityourself", "tags": ["doityourself", "building", "supply"], "sources": ["overture"], "website": "http://www.convoy-supply.com", "phone": "+12537372420", "address": "19041 80th Ave S"}, "geometry": {"type": "Point", "coordinates": [-122.2341766, 47.4303474]}}]}