{"type": "FeatureCollection", "features": [{"type": "Feature", "properties": {"id": 24887711, "name": "Fishers Pond Park", "category": "park", "tags": ["park"], "sources": ["osm"]}, "geometry": {"type": "Point", "coordinates": [-122.3413656, 47.315995]}}]}