{"type": "FeatureCollection", "features": [{"type": "Feature", "properties": {"id": "078567b9-7ad9-4344-81f2-caa51e50a19c", "name": "Starbucks", "category": "cafe", "tags": ["cafe", "coffee"], "sources": ["overture"], "phone": "2064335131", "address": "2580 S 156th St Sea Seatac Relocate O F Nr Espl"}, "geometry": {"type": "Point", "coordinates": [-122.3007736, 47.4634781]}}, {"type": "Feature", "properties": {"id": "fb52bc37-91dc-4031-9b7d-2504c6ac9911", "name": "China First Express", "category": "restaurant", "tags": ["restaurant"], "sources": ["overture"], "website": "http://www.chinafirstseattle.com", "phone": "(206) 433-1990", "address": "2580 S 156th St"}, "geometry": {"type": "Point", "coordinates": [-122.3009644, 47.4639854]}}]}