{"type": "FeatureCollection", "features": [{"type": "Feature", "properties": {"id": 163608508, "name": "Lake Boren Park", "category": "park", "tags": ["park"], "sources": ["osm"], "address": "13058 Southeast 84th Way", "hours": "07:00-dusk"}, "geometry": {"type": "Point", "coordinates": [-122.165176, 47.5296185]}}, {"type": "Feature", "properties": {"id": "eb4b53d5-4bf8-4026-a041-de9b373ca0b3", "name": "Lake Boren Park", "category": "park", "tags": ["park"], "sources": ["overture"], "website": "http://www.ci.newcastle.wa.us/ch_cds_pw_pet_parks_Lake_Boren_Park.asp", "phone": "+14256494444", "address": "13058 SE 84th Way"}, "geometry": {"type": "Point", "coordinates": [-122.1655884, 47.5283546]}}]}