{"type": "FeatureCollection", "features": [{"type": "Feature", "properties": {"id": 405412059, "name": "MacDonald Memorial Preserve", "category": "park", "tags": ["park"], "sources": ["osm"]}, "geometry": {"type": "Point", "coordinates": [-122.2466565, 47.7132981]}}, {"type": "Feature", "properties": {"id": "710ae497-be1c-4b1f-ad3f-2c83c0941769", "name": "Warren G. Magnussen Off Leash Dog Park", "category": "park", "tags": ["park", "dog"], "sources": ["overture"]}, "geometry": {"type": "Point", "coordinates": [-122.2464523, 47.7135544]}}]}