{"type": "FeatureCollection", "features": [{"type": "Feature", "properties": {"id": 442656236, "name": "Park Orchard Park", "category": "park", "tags": ["park"], "sources": ["osm", "overture"], "website": "http://www.kent.k12.wa.us/po", "phone": "+12538565000", "address": "11058 SE 230th St"}, "geometry": {"type": "Point", "coordinates": [-122.1929522, 47.3971741]}}, {"type": "Feature", "properties": {"id": "b0090a8e-93c0-4154-a122-332cee810353", "name": "Park Orchard Park", "category": "park", "tags": ["park"], "sources": ["overture"], "website": "http://www.kent.k12.wa.us/po", "address": "112TH Pl SE"}, "geometry": {"type": "Point", "coordinates": [-122.1947861, 47.3962631]}}]}