{"type": "FeatureCollection", "features": [{"type": "Feature", "properties": {"id": "75a7edcd-a3be-415c-923a-c7eb05f87645", "name": "Pagliacci Pizza", "category": "restaurant", "tags": ["restaurant", "pizza"], "sources": ["overture"], "website": "http://www.pagliacci.com", "phone": "(206) 726-1717", "address": "563 Bellevue Way SE", "stations": [{"stopCode": 55, "lines": "2", "name": "Mercer Island Station", "walkingMeters": 1085, "walkingSeconds": 782, "band": 15}]}, "geometry": {"type": "Point", "coordinates": [-122.2228012, 47.5847015]}}, {"type": "Feature", "properties": {"id": 3653020502, "name": "The Source", "category": "artwork", "tags": ["artwork"], "sources": ["osm"], "stations": [{"stopCode": 55, "lines": "2", "name": "Mercer Island Station", "walkingMeters": 776, "walkingSeconds": 560, "band": 10}]}, "geometry": {"type": "Point", "coordinates": [-122.225522, 47.5876584]}}, {"type": "Feature", "properties": {"id": 4912168255, "name": "Orbits and Pieces", "category": "artwork", "tags": ["artwork"], "sources": ["osm"], "stations": [{"stopCode": 55, "lines": "2", "name": "Mercer Island Station", "walkingMeters": 685, "walkingSeconds": 495, "band": 10}]}, "geometry": {"type": "Point", "coordinates": [-122.2276029, 47.5898008]}}, {"type": "Feature", "properties": {"id": 144686887, "name": "Upper Luther Burbank Park", "category": "park", "tags": ["park"], "sources": ["osm"]}, "geometry": {"type": "Point", "coordinates": [-122.2233723, 47.5802866]}}]}