{"type": "FeatureCollection", "features": [{"type": "Feature", "properties": {"id": 461326753, "name": "Stonefield Park 1", "category": "park", "tags": ["park"], "sources": ["osm"]}, "geometry": {"type": "Point", "coordinates": [-122.1225947, 47.3655351]}}, {"type": "Feature", "properties": {"id": 470497683, "name": "Fairfield Neighborhood Park", "category": "park", "tags": ["park"], "sources": ["osm"]}, "geometry": {"type": "Point", "coordinates": [-122.1254656, 47.3699792]}}, {"type": "Feature", "properties": {"id": 478681286, "name": "Fairfield Neighborhood Park", "category": "park", "tags": ["park"], "sources": ["osm"]}, "geometry": {"type": "Point", "coordinates": [-122.1272508, 47.3682497]}}, {"type": "Feature", "properties": {"id": "e2593462-ff45-4bda-9301-c80745d20cb7", "name": "The Reserve", "category": "park", "tags": ["park"], "sources": ["overture"], "address": "25907 161st Ct SE"}, "geometry": {"type": "Point", "coordinates": [-122.1279984, 47.3694115]}}]}