{"type": "FeatureCollection", "features": [{"type": "Feature", "properties": {"id": 419546354, "name": "Forest Landing", "category": "park", "tags": ["park"], "sources": ["osm"], "website": "http://www.mercergov.org/Page.asp?NavID=1448"}, "geometry": {"type": "Point", "coordinates": [-122.2333997, 47.5682491]}}, {"type": "Feature", "properties": {"id": 419546357, "name": "Miller Landing", "category": "park", "tags": ["park"], "sources": ["osm"], "website": "http://www.mercergov.org/Page.asp?NavID=1448"}, "geometry": {"type": "Point", "coordinates": [-122.2306043, 47.5603212]}}]}