{"type": "FeatureCollection", "features": [{"type": "Feature", "properties": {"id": "ad4a84d9-a018-4510-8a8d-a1e45fce0282", "name": "The Trails of Redmond", "category": "attraction", "tags": ["attraction", "landmark", "historical", "building"], "sources": ["overture"], "website": "https://www.essexapartmenthomes.com/apartments/redmond/the-trails-of-redmond", "phone": "+14254341974", "address": "16539 NE 35th Ct"}, "geometry": {"type": "Point", "coordinates": [-122.1179276, 47.6443138]}}, {"type": "Feature", "properties": {"id": "a3c2bbcc-5919-47a6-af32-35c67867d18d", "name": "Villa Marina", "category": "attraction", "tags": ["attraction", "landmark", "historical", "building"], "sources": ["overture"], "website": "http://www.vmcondos.com/wp", "phone": "+14252420512", "address": "17108 NE 45th St"}, "geometry": {"type": "Point", "coordinates": [-122.1105042, 47.6499901]}}, {"type": "Feature", "properties": {"id": 1427461434, "name": "Flicker's Pond", "category": "park", "tags": ["park"], "sources": ["osm"], "address": "Northeast 40th Street"}, "geometry": {"type": "Point", "coordinates": [-122.1147141, 47.6457803]}}, {"type": "Feature", "properties": {"id": "bb629f04-4a43-436e-a177-5dd1381f2499", "name": "Club At Trails Of Redmond", "category": "fitness_centre", "tags": ["fitness-centre", "gym"], "sources": ["overture"], "website": "http://www.essexapartmenthomes.com/washington/seattle-area-apartments/redmond-apartments/the-trails-redmond", "phone": "(425) 883-0000", "address": "16539 NE 35th Ct"}, "geometry": {"type": "Point", "coordinates": [-122.1196976, 47.6438942]}}]}