{"type": "FeatureCollection", "features": [{"type": "Feature", "properties": {"id": "8978b3bc-61b0-467a-a0e4-531f50542811", "name": "Clark Lake Park", "category": "park", "tags": ["park"], "sources": ["overture"], "website": "http://www.ci.kent.wa.us/content.aspx?id=10556", "phone": "+12538565000", "address": "12520 SE 240th St"}, "geometry": {"type": "Point", "coordinates": [-122.1742401, 47.3866806]}}]}