{"type": "FeatureCollection", "features": [{"type": "Feature", "properties": {"id": 1225564499, "name": "Betz Winery", "category": "attraction", "tags": ["attraction", "winery", "wine"], "sources": ["osm"]}, "geometry": {"type": "Point", "coordinates": [-122.133715, 47.719082]}}, {"type": "Feature", "properties": {"id": "60adaad6-e84c-4a87-bd12-ca51fdf14ca6", "name": "Betz Family Winery", "category": "wine", "tags": ["wine", "winery"], "sources": ["overture"], "website": "http://www.betzfamilywinery.com/", "phone": "+14258619823", "address": "13244 Woodinville Redmond Rd NE"}, "geometry": {"type": "Point", "coordinates": [-122.1338043, 47.7191048]}}, {"type": "Feature", "properties": {"id": "51cd1749-398d-494d-b088-66fe0195a2c3", "name": "Vintner's Door", "category": "wine", "tags": ["wine", "winery"], "sources": ["overture"], "website": "http://www.vintnersdoor.business.site/", "phone": "+14254668237", "address": "13246 Woodinville Redmond Rd NE"}, "geometry": {"type": "Point", "coordinates": [-122.1344757, 47.7198029]}}]}