{"type": "FeatureCollection", "features": [{"type": "Feature", "properties": {"id": "4db5f5f0-423b-4040-a84b-31492fc3ed2b", "name": "Hideaway Lodge Bed and Breakfast", "category": "guest_house", "tags": ["guest-house", "bed", "breakfast"], "sources": ["overture"], "website": "http://www.hideawaylodgebnb.com/", "phone": "+14252862240", "address": "15228 NE 173rd St"}, "geometry": {"type": "Point", "coordinates": [-122.134758, 47.7533073]}}]}