{"type": "FeatureCollection", "features": [{"type": "Feature", "properties": {"id": 470485510, "name": "Carriagewood Neighborhood Park", "category": "park", "tags": ["park"], "sources": ["osm"]}, "geometry": {"type": "Point", "coordinates": [-122.136463, 47.4387725]}}]}