{"type": "FeatureCollection", "features": [{"type": "Feature", "properties": {"id": "1e2330b4-019f-446b-8eef-e1197912e214", "name": "Soos Creek Park", "category": "park", "tags": ["park"], "sources": ["overture"], "website": "http://sooscreekfarm.com/", "address": "152nd Way SE"}, "geometry": {"type": "Point", "coordinates": [-122.1572037, 47.3964882]}}]}