{"type": "FeatureCollection", "features": [{"type": "Feature", "properties": {"id": "19f55449-2442-4998-a0bc-73917564227b", "name": "Lake Meridian Shores Apartment Homes", "category": "attraction", "tags": ["attraction", "landmark", "historical", "building"], "sources": ["overture"], "website": "http://www.lakemeridianshores.com", "phone": "+12536316733", "address": "14200 SE 272nd St"}, "geometry": {"type": "Point", "coordinates": [-122.1529465, 47.358326]}}, {"type": "Feature", "properties": {"id": 442655538, "name": "Meridian Glen Park", "category": "park", "tags": ["park"], "sources": ["osm", "overture"], "phone": "+12538565000", "address": "27535 137th Ave SE"}, "geometry": {"type": "Point", "coordinates": [-122.1591847, 47.3547171]}}]}