{"type": "FeatureCollection", "features": [{"type": "Feature", "properties": {"id": 422782114, "name": "Green Tree Park", "category": "park", "tags": ["park"], "sources": ["osm", "overture"], "website": "http://www.kentwa.gov/content.aspx?id=25606", "phone": "+12538565000", "address": "120th Ave SE and, SE 216th St"}, "geometry": {"type": "Point", "coordinates": [-122.1809728, 47.4091812]}}, {"type": "Feature", "properties": {"id": "cb5087f5-0d62-4d88-921a-8e399268b275", "name": "Emerald Park Playground", "category": "park", "tags": ["park"], "sources": ["overture"]}, "geometry": {"type": "Point", "coordinates": [-122.1812134, 47.4084053]}}]}