{"type": "FeatureCollection", "features": [{"type": "Feature", "properties": {"id": 12646797238, "name": "Hummingbird", "category": "artwork", "tags": ["artwork"], "sources": ["osm"], "website": "https://www.biodesignstudio.com/post/city-of-kirkland-greenway-art-series-entitled-biophilia"}, "geometry": {"type": "Point", "coordinates": [-122.1698737, 47.6861846]}}]}