{"type": "FeatureCollection", "features": [{"type": "Feature", "properties": {"id": 1430791610, "name": "Angle Lake Manor Private Beach", "category": "park", "tags": ["park"], "sources": ["osm"]}, "geometry": {"type": "Point", "coordinates": [-122.28929, 47.4291214]}}, {"type": "Feature", "properties": {"id": "387c89fc-e3ca-4431-b079-e3d934cc180f", "name": "Improvements Done Right", "category": "doityourself", "tags": ["doityourself", "building", "supply"], "sources": ["overture"], "website": "http://improvementsdoneright.com", "phone": "(206) 399-4965", "address": "3415 S 198th St", "stations": [{"stopCode": 65, "lines": "1", "name": "Angle Lake Station", "walkingMeters": 787, "walkingSeconds": 572, "band": 10}]}, "geometry": {"type": "Point", "coordinates": [-122.2895203, 47.4240379]}}]}