{"type": "FeatureCollection", "features": [{"type": "Feature", "properties": {"id": 480083703, "name": "English Hill Greenbelt", "category": "park", "tags": ["park"], "sources": ["osm"]}, "geometry": {"type": "Point", "coordinates": [-122.1104961, 47.727612]}}, {"type": "Feature", "properties": {"id": "c03a1f1f-dd42-4900-9af2-32c663baf22e", "name": "Trouvaille Winery", "category": "wine", "tags": ["wine", "winery"], "sources": ["overture"], "website": "http://www.trouvaillewinery.com", "phone": "+14258618020", "address": "16735 NE 139th Pl"}, "geometry": {"type": "Point", "coordinates": [-122.1159592, 47.7244492]}}]}