{"type": "FeatureCollection", "features": [{"type": "Feature", "properties": {"id": 29544113, "name": "Viewpoint Open Space", "category": "park", "tags": ["park"], "sources": ["osm", "overture"], "website": "http://redmond.gov/cms/one.aspx?pageId=4167", "phone": "+14255562900", "address": "17541 NE 24th St", "hours": "dawn-dusk"}, "geometry": {"type": "Point", "coordinates": [-122.1050093, 47.6293796]}}, {"type": "Feature", "properties": {"id": 73530090, "name": "Tam O'Shanter Park", "category": "park", "tags": ["park"], "sources": ["osm"], "website": "http://www.ci.bellevue.wa.us/tam_oshanter.htm", "address": "1655 173rd Avenue Northeast"}, "geometry": {"type": "Point", "coordinates": [-122.1059851, 47.6258175]}}, {"type": "Feature", "properties": {"id": "0afea3ed-2a57-4ba8-96c5-094693f60b7b", "name": "Tam O'Shanter Park", "category": "park", "tags": ["park"], "sources": ["overture"], "website": "http://www.bellevuewa.gov/tam_oshanter.htm", "phone": "(425) 452-6885", "address": "1655 173rd Ave NE"}, "geometry": {"type": "Point", "coordinates": [-122.1078796, 47.624733]}}, {"type": "Feature", "properties": {"id": 73530156, "name": "Viewpont Open Space", "category": "park", "tags": ["park"], "sources": ["osm"], "website": "https://www.redmond.gov/insidecityhall/parksrec/parks/vopenspace.asp", "address": "17541 Northeast 24th Street"}, "geometry": {"type": "Point", "coordinates": [-122.1050093, 47.6293796]}}]}