{"type": "FeatureCollection", "features": [{"type": "Feature", "properties": {"id": 76743718, "name": "Paramount School Park", "category": "park", "tags": ["park"], "sources": ["osm"], "stations": [{"stopCode": 43, "lines": "1,2", "name": "Shoreline South/148th Station", "walkingMeters": 1108, "walkingSeconds": 796, "band": 15}]}, "geometry": {"type": "Point", "coordinates": [-122.3196692, 47.7402713]}}]}