{"type": "FeatureCollection", "features": [{"type": "Feature", "properties": {"id": "eaae1b8d-fd6d-4a6a-bc02-ad36f4571aa8", "name": "PF Chang's China Bistro", "category": "restaurant", "tags": ["restaurant"], "sources": ["overture"], "website": "https://www.pfchangs.com/?storeid=9971", "phone": "+14259212100", "address": "29th Pl W"}, "geometry": {"type": "Point", "coordinates": [-122.2728119, 47.8063698]}}, {"type": "Feature", "properties": {"id": "e5d79fed-c05d-4f41-999e-c78a384e5125", "name": "Chandler Park, Lynnwood, Washington", "category": "park", "tags": ["park"], "sources": ["overture"]}, "geometry": {"type": "Point", "coordinates": [-122.2755661, 47.8014717]}}]}