{"type": "FeatureCollection", "features": [{"type": "Feature", "properties": {"id": 172710029, "name": "City Hall Park", "category": "park", "tags": ["park"], "sources": ["osm"]}, "geometry": {"type": "Point", "coordinates": [-122.3461305, 47.4448928]}}, {"type": "Feature", "properties": {"id": "cf5e7547-ed23-4f38-91b7-5874a7ecdd2d", "name": "City Hall Park", "category": "park", "tags": ["park"], "sources": ["overture"], "website": "http://cityhallpark6.placeweb.site", "address": "899 SW 174th St"}, "geometry": {"type": "Point", "coordinates": [-122.345932, 47.4458466]}}, {"type": "Feature", "properties": {"id": "e6dcc16b-b89f-48a6-bcbd-ec874a8f0706", "name": "Normandy Park City Hall", "category": "park", "tags": ["park"], "sources": ["overture"], "website": "http://www.ci.normandy-park.wa.us", "phone": "(206) 248-7603", "address": "801 SW 174th St"}, "geometry": {"type": "Point", "coordinates": [-122.3456802, 47.4456673]}}, {"type": "Feature", "properties": {"id": 12269406402, "name": "Normandy Park Lockers", "category": "library", "tags": ["library", "wifi"], "sources": ["osm"], "website": "https://kcls.org/locations/165/", "address": "801 Southwest 174th Street", "hours": "00:00-23:45"}, "geometry": {"type": "Point", "coordinates": [-122.3455364, 47.4456143]}}]}