{"type": "FeatureCollection", "features": [{"type": "Feature", "properties": {"id": 1259534298, "name": "Renton Fish & Game Club", "category": "sports_centre", "tags": ["sports-centre"], "sources": ["osm"]}, "geometry": {"type": "Point", "coordinates": [-122.109223, 47.470781]}}, {"type": "Feature", "properties": {"id": "2ec8bfee-b03d-4287-99d6-a12ba4f129fa", "name": "S.A.S. Fitness", "category": "fitness_centre", "tags": ["fitness-centre", "gym"], "sources": ["overture"], "website": "http://www.sas-fit.com", "phone": "+12068500174", "address": "14215 177th Ave SE"}, "geometry": {"type": "Point", "coordinates": [-122.1051407, 47.4745636]}}]}