{"type": "FeatureCollection", "features": [{"type": "Feature", "properties": {"id": "3675bbab-6827-4524-8660-ecd178de5548", "name": "La Rielera LLC", "category": "restaurant", "tags": ["restaurant", "mexican", "texmex", "taco"], "sources": ["overture"], "website": "https://www.larieleraseattle.com/", "phone": "+12065796092", "address": "11850 Des Moines Memorial Dr S"}, "geometry": {"type": "Point", "coordinates": [-122.3101807, 47.4963799]}}, {"type": "Feature", "properties": {"id": "407d45e1-f26a-4509-81dc-18012408d883", "name": "Birrieria La Sabrosa de Los Mochis", "category": "restaurant", "tags": ["restaurant", "mexican", "latin-american"], "sources": ["overture"], "phone": "+12069417158", "address": "12610 Des Moines Memorial Dr S"}, "geometry": {"type": "Point", "coordinates": [-122.3102493, 47.4901047]}}, {"type": "Feature", "properties": {"id": 409292812, "name": "Southern Heights Park", "category": "park", "tags": ["park"], "sources": ["osm", "overture"], "phone": "+12069883700", "address": "12025 14th Ave S"}, "geometry": {"type": "Point", "coordinates": [-122.3160562, 47.4950413]}}]}