{"type": "FeatureCollection", "features": [{"type": "Feature", "properties": {"id": "78824272-e110-430f-ab2f-90c921ae4e86", "name": "Kently Pointe Apartments", "category": "attraction", "tags": ["attraction", "landmark", "historical", "building"], "sources": ["overture"], "website": "https://www.kentlypointe.com/", "phone": "+18552568572", "address": "4724 S 272nd St"}, "geometry": {"type": "Point", "coordinates": [-122.2730408, 47.3587456]}}]}