{"type": "FeatureCollection", "features": [{"type": "Feature", "properties": {"id": 5235872930, "name": "Meridian Valley Country Club Restaurant", "category": "restaurant", "tags": ["restaurant"], "sources": ["osm"]}, "geometry": {"type": "Point", "coordinates": [-122.1572587, 47.3784939]}}, {"type": "Feature", "properties": {"id": 442653923, "name": "Eastridge Park", "category": "park", "tags": ["park"], "sources": ["osm", "overture"], "website": "http://eastridgepark.com", "phone": "+12538565000", "address": "&, 143rd Ave SE & SE 257th Pl"}, "geometry": {"type": "Point", "coordinates": [-122.1517999, 47.3703742]}}]}