{"type": "FeatureCollection", "features": [{"type": "Feature", "properties": {"id": "cbbefed7-9396-41d7-aad9-aacc7b8004a5", "name": "Homewood Terrace", "category": "attraction", "tags": ["attraction", "landmark", "historical", "building"], "sources": ["overture"], "website": "https://sites.google.com/site/homewoodterrace/", "phone": "+12538399435", "address": "30030 38th Ave S"}, "geometry": {"type": "Point", "coordinates": [-122.2852097, 47.3321724]}}, {"type": "Feature", "properties": {"id": 25124052, "name": "Camelot Park", "category": "park", "tags": ["park"], "sources": ["osm"]}, "geometry": {"type": "Point", "coordinates": [-122.2801819, 47.3380501]}}]}