{"type": "FeatureCollection", "features": [{"type": "Feature", "properties": {"id": "45d25f64-9191-47f3-9555-a0836a1a4c12", "name": "Boiler & Steam Systems", "category": "doityourself", "tags": ["doityourself", "building", "supply"], "sources": ["overture"], "website": "http://www.boilerandsteam.com", "phone": "(425) 614-0784", "address": "4675 174th Ct SE"}, "geometry": {"type": "Point", "coordinates": [-122.1063766, 47.5607147]}}]}