{"type": "FeatureCollection", "features": [{"type": "Feature", "properties": {"id": "633d7075-0387-4de9-a8c1-0b773c641c73", "name": "Covey Ridge Condominiums", "category": "attraction", "tags": ["attraction", "landmark", "historical", "building"], "sources": ["overture"], "address": "8805 166th Ave NE"}, "geometry": {"type": "Point", "coordinates": [-122.1198807, 47.680748]}}, {"type": "Feature", "properties": {"id": "0c14780f-60b8-4266-bf4b-2156a140bf91", "name": "Melrose on 91", "category": "attraction", "tags": ["attraction", "landmark", "historical", "building"], "sources": ["overture"], "website": "https://www.melroseon91.com/?rcstdid=MTE%3D-aKFOxiSL8lQ%3D", "phone": "+18332404559", "address": "16518 NE 91st St"}, "geometry": {"type": "Point", "coordinates": [-122.1193924, 47.6832886]}}, {"type": "Feature", "properties": {"id": 480795320, "name": "Redmond Bike Park", "category": "park", "tags": ["park"], "sources": ["osm", "overture"], "website": "http://www.redmondkirklandveterinary.com", "phone": "+1-425-556-2300", "address": "9916 171st Ave NE", "hours": "dawn-dusk"}, "geometry": {"type": "Point", "coordinates": [-122.1113924, 47.6888294]}}, {"type": "Feature", "properties": {"id": 1304960900, "name": "Heritage Woods Playground", "category": "playground", "tags": ["playground"], "sources": ["osm"]}, "geometry": {"type": "Point", "coordinates": [-122.1194081, 47.6836184]}}]}