{"type": "FeatureCollection", "features": [{"type": "Feature", "properties": {"id": "344da1f2-240e-45cc-9572-c7e49c6c4d6d", "name": "Onyx Apartments", "category": "attraction", "tags": ["attraction", "landmark", "historical", "building"], "sources": ["overture"], "website": "https://www.theonyxaptsredmond.com/", "phone": "+18332177326", "address": "4850 156th Ave NE", "stations": [{"stopCode": 63, "lines": "2", "name": "Redmond Technology Center Station", "walkingMeters": 1001, "walkingSeconds": 723, "band": 15}]}, "geometry": {"type": "Point", "coordinates": [-122.1313324, 47.652317]}}, {"type": "Feature", "properties": {"id": 114464547, "name": "Westside Park", "category": "park", "tags": ["park"], "sources": ["osm"], "website": "https://www.redmond.gov/facilities/facility/details/Westside-Park-57", "phone": "+1-425-556-2300", "address": "5810 156th Avenue Northeast", "hours": "dawn-dusk"}, "geometry": {"type": "Point", "coordinates": [-122.1300821, 47.6592587]}}, {"type": "Feature", "properties": {"id": "c3c99efb-a7fe-4548-8e3d-57a9d475cc75", "name": "Westside Park", "category": "park", "tags": ["park"], "sources": ["overture"], "website": "http://www.redmond.gov/cms/one.aspx?portalId=169&pageId=4179", "phone": "+14255562311", "address": "5810 156th Ave NE"}, "geometry": {"type": "Point", "coordinates": [-122.1324158, 47.6592216]}}, {"type": "Feature", "properties": {"id": "98d3ea53-9068-4d51-8a12-aa30e96b60e3", "name": "Nintendo Campus", "category": "toys", "tags": ["toys"], "sources": ["overture"], "phone": "+13122019672", "address": "4820 150th Ave NE", "stations": [{"stopCode": 63, "lines": "2", "name": "Redmond Technology Center Station", "walkingMeters": 1273, "walkingSeconds": 916, "band": 15}]}, "geometry": {"type": "Point", "coordinates": [-122.139473, 47.6520386]}}]}