{"type": "FeatureCollection", "features": [{"type": "Feature", "properties": {"id": 175817442, "name": "Soos Creek Park and Trails - Kent", "category": "park", "tags": ["park"], "sources": ["osm"]}, "geometry": {"type": "Point", "coordinates": [-122.1414665, 47.3609045]}}]}