{"type": "FeatureCollection", "features": [{"type": "Feature", "properties": {"id": "e1217210-fdb9-4810-90ce-a7675af25a42", "name": "Dixie's BBQ", "category": "restaurant", "tags": ["restaurant", "barbecue"], "sources": ["overture"], "website": "http://ljporter.com/", "phone": "(425) 828-2460", "address": "11522 Northup Way"}, "geometry": {"type": "Point", "coordinates": [-122.186554, 47.6336403]}}, {"type": "Feature", "properties": {"id": "6ab61270-6a72-4f23-abb3-5cb7024bc920", "name": "Lowe's Home Improvement - CLOSED", "category": "hardware", "tags": ["hardware"], "sources": ["overture"], "website": "http://www.lowes.com/store/WA-Bellevue/0040", "phone": "(425) 646-9031", "address": "11959 Northup Way", "stations": [{"stopCode": 60, "lines": "2", "name": "Spring District/120th Station", "walkingMeters": 1161, "walkingSeconds": 835, "band": 15}]}, "geometry": {"type": "Point", "coordinates": [-122.1822586, 47.6310539]}}, {"type": "Feature", "properties": {"id": 391112327, "name": "Pediatric Associates", "category": "clinic", "tags": ["clinic"], "sources": ["osm"], "address": "2700 Northup Way"}, "geometry": {"type": "Point", "coordinates": [-122.1885533, 47.6349217]}}]}