{"type": "FeatureCollection", "features": [{"type": "Feature", "properties": {"id": "118c04f9-ccc8-4086-9498-6e76f5b8cc15", "name": "Sammamish River Regional Park", "category": "park", "tags": ["park"], "sources": ["overture"], "website": "https://www.discovertheforest.org/", "phone": "+12062968687", "address": "15200 NE 116th St"}, "geometry": {"type": "Point", "coordinates": [-122.1427155, 47.7044678]}}, {"type": "Feature", "properties": {"id": "225b9c1d-c4ac-4ff9-98ad-91fb68963819", "name": "Sixty Acres Park", "category": "park", "tags": ["park"], "sources": ["overture"], "website": "http://60acres.org", "phone": "+14258211741", "address": "15200 NE 116th St"}, "geometry": {"type": "Point", "coordinates": [-122.1401749, 47.7047234]}}]}