{"type": "FeatureCollection", "features": [{"type": "Feature", "properties": {"id": 33721382, "name": "Heritage Park", "category": "park", "tags": ["park"], "sources": ["osm", "overture"], "website": "http://www.myparksandrecreation.com/ParksTrails/Details.aspx?pid=147", "phone": "+19283759929", "address": "111 Waverly Way"}, "geometry": {"type": "Point", "coordinates": [-122.211581, 47.6784289]}}, {"type": "Feature", "properties": {"id": 55786153, "name": "Lake Avenue West Street End Park", "category": "park", "tags": ["park"], "sources": ["osm", "overture"], "website": "https://www.kirklandwa.gov/Government/Departments/Parks-and-Community-Services/Online-Parks-Guide/Lake-Avenue-West-Street-End-Park", "address": "297 Lake Ave W", "hours": "08:00-dusk"}, "geometry": {"type": "Point", "coordinates": [-122.2137953, 47.6798767]}}]}