{"type": "FeatureCollection", "features": [{"type": "Feature", "properties": {"id": "490d660a-f0d8-44c2-9f97-a88c01252988", "name": "Young's Market Company of Washington", "category": "alcohol", "tags": ["alcohol"], "sources": ["overture"], "website": "http://www.youngsmarket.com", "phone": "+18003176150", "address": "20301 59th Pl S"}, "geometry": {"type": "Point", "coordinates": [-122.2626038, 47.4194031]}}]}