{"type": "FeatureCollection", "features": [{"type": "Feature", "properties": {"id": "e1fe7c91-ccae-45f4-afcd-1fdc476b337c", "name": "Bridle Trails State Park", "category": "park", "tags": ["park"], "sources": ["overture"], "website": "http://www.parks.wa.gov/parks/?selectedpark=Bridle+Trails", "phone": "+14253073578", "address": "4001 132nd Ave NE"}, "geometry": {"type": "Point", "coordinates": [-122.1647568, 47.6464119]}}]}