{"type": "FeatureCollection", "features": [{"type": "Feature", "properties": {"id": 119995926, "name": "Earlington Park", "category": "park", "tags": ["park"], "sources": ["osm", "overture"], "website": "https://rentonwa.gov/cms/One.aspx?portalId=7922741&pageId=8838268", "phone": "+14254306600", "address": "Earlington Park, 272 Thomas Ave SW"}, "geometry": {"type": "Point", "coordinates": [-122.2274294, 47.4805599]}}, {"type": "Feature", "properties": {"id": "90bcfb2a-59a5-4cb3-809f-dc0cca453151", "name": "Earlington Park", "category": "park", "tags": ["park"], "sources": ["overture"], "website": "https://rentonwa.gov/cms/One.aspx?portalId=7922741&pageId=8838268", "phone": "(425) 430-6600", "address": "281 Thomas Ave SW"}, "geometry": {"type": "Point", "coordinates": [-122.2287445, 47.4801331]}}, {"type": "Feature", "properties": {"id": 926942991, "name": "Earlington Townhomes Neighborhood Park", "category": "park", "tags": ["park"], "sources": ["osm"]}, "geometry": {"type": "Point", "coordinates": [-122.2284266, 47.4848769]}}]}