{"type": "FeatureCollection", "features": [{"type": "Feature", "properties": {"id": 5228387521, "name": "Bogey's Public House", "category": "restaurant", "tags": ["restaurant", "pub", "bar-and-grill"], "sources": ["osm", "overture"], "website": "https://www.bogeyspublichouse.com/", "phone": "+12538761957", "address": "29630 Green River Rd SE"}, "geometry": {"type": "Point", "coordinates": [-122.2066292, 47.3361258]}}, {"type": "Feature", "properties": {"id": "f5bf1b40-ec72-44d2-a429-77222190edf3", "name": "Mens Club at Auburn Golf Course", "category": "sports_centre", "tags": ["sports-centre", "sports", "club", "league"], "sources": ["overture"], "website": "https://mensclubagc.org/", "phone": "+12538332350", "address": "29630 Green River Rd SE"}, "geometry": {"type": "Point", "coordinates": [-122.207901, 47.3367195]}}]}