{"type": "FeatureCollection", "features": [{"type": "Feature", "properties": {"id": "a028e111-4b8b-4225-b785-dd1efe932e8d", "name": "Kubota Garden Foundation", "category": "garden", "tags": ["garden", "botanical"], "sources": ["overture"], "phone": "+12067255060", "address": "10915 51st Ave S"}, "geometry": {"type": "Point", "coordinates": [-122.2704697, 47.5045547]}}, {"type": "Feature", "properties": {"id": 653521968, "name": "Checkers III", "category": "convenience", "tags": ["convenience"], "sources": ["osm"], "address": "10359 51st Avenue South"}, "geometry": {"type": "Point", "coordinates": [-122.2703827, 47.5071461]}}]}