{"type": "FeatureCollection", "features": [{"type": "Feature", "properties": {"id": 32869952, "name": "Penguin Park", "category": "park", "tags": ["park"], "sources": ["osm", "overture"], "address": "3804 NE 94th St"}, "geometry": {"type": "Point", "coordinates": [-122.2878665, 47.696957]}}, {"type": "Feature", "properties": {"id": 55174405, "name": "Inverness Ravine", "category": "park", "tags": ["park"], "sources": ["osm"], "website": "https://www.seattle.gov/parks/allparks/inverness-ravine-park"}, "geometry": {"type": "Point", "coordinates": [-122.2807021, 47.6911018]}}]}