{"type": "FeatureCollection", "features": [{"type": "Feature", "properties": {"id": 659999556, "name": "Marisol Community Park", "category": "park", "tags": ["park"], "sources": ["osm"]}, "geometry": {"type": "Point", "coordinates": [-122.177099, 47.8041729]}}, {"type": "Feature", "properties": {"id": 11179298168, "name": "Creart Studioz", "category": "art", "tags": ["art"], "sources": ["osm"], "phone": "+1-919-597-8577", "address": "21319 42nd Avenue Southeast", "hours": "Mo-Su 10:30-19:00"}, "geometry": {"type": "Point", "coordinates": [-122.1762879, 47.804072]}}]}